[1,0,0,[["cc.JsonAsset",["_name","json"],1]],[[0,0,1,3]],[[0,"TaskDesc",[{"id":101,"name":"登录{0}天","type":0,"jumpId":1,"jumpId2":3},{"id":102,"name":"累计登录{0}天","type":1,"jumpId":1,"jumpId2":4},{"id":103,"name":"在线{0}分钟","type":1,"jumpId":1,"jumpId2":5},{"id":201,"name":"观看{0}个广告","type":1,"jumpId":1,"jumpId2":6},{"id":202,"name":"累计观看{0}个广告","type":0,"jumpId":1,"jumpId2":7},{"id":203,"name":"完成{0}次充值","type":1,"jumpId":1,"jumpId2":8},{"id":204,"name":"累计充值{0}元","type":1,"jumpId":1,"jumpId2":9},{"id":301,"name":"获得{0}个钻石","type":1,"jumpId":1,"jumpId2":10},{"id":302,"name":"获得{0}金币","type":1,"jumpId":1,"jumpId2":11},{"id":303,"name":"累计获得{0}个钻石","type":0,"jumpId":1,"jumpId2":12},{"id":304,"name":"累计获得{0}金币","type":0,"jumpId":1,"jumpId2":13},{"id":311,"name":"累计消耗{0}钻石","type":0,"jumpId":1,"jumpId2":14},{"id":312,"name":"消耗{0}钻石","type":1,"jumpId":1,"jumpId2":15},{"id":313,"name":"累计消耗{0}金币","type":0,"jumpId":1,"jumpId2":16},{"id":401,"name":"通关小山城寨第{0}波","type":2,"jumpId":1,"jumpId2":17},{"id":402,"name":"通关断水流道场第{0}波","type":2,"jumpId":1,"jumpId2":18},{"id":403,"name":"通关戚家大院第{0}波","type":2,"jumpId":1,"jumpId2":19},{"id":404,"name":"通关牌神风云第{0}波","type":2,"jumpId":1,"jumpId2":20},{"id":405,"name":"通关盘丝洞第{0}波","type":2,"jumpId":1,"jumpId2":21},{"id":406,"name":"通关新武擂台第{0}波","type":2,"jumpId":1,"jumpId2":22},{"id":407,"name":"通关华府大堂第{0}波","type":2,"jumpId":1,"jumpId2":23},{"id":408,"name":"通关东郊皇陵第{0}波","type":2,"jumpId":1,"jumpId2":24},{"id":409,"name":"通关猪肉摊第{0}波","type":2,"jumpId":1,"jumpId2":25},{"id":410,"name":"通关研究中心第{0}波","type":2,"jumpId":1,"jumpId2":26},{"id":411,"name":"通关破茧成蝶I第{0}波","type":2,"jumpId":1,"jumpId2":27},{"id":412,"name":"通关破茧成蝶II第{0}波","type":2,"jumpId":1,"jumpId2":28},{"id":413,"name":"通关破茧成蝶III第{0}波","type":2,"jumpId":1,"jumpId2":29},{"id":414,"name":"通关破茧成蝶IV第{0}波","type":2,"jumpId":1,"jumpId2":30},{"id":415,"name":"通关月光宝盒I第{0}波","type":2,"jumpId":1,"jumpId2":31},{"id":416,"name":"通关月光宝盒II第{0}波","type":2,"jumpId":1,"jumpId2":32},{"id":417,"name":"通关月光宝盒III第{0}波","type":2,"jumpId":1,"jumpId2":33},{"id":418,"name":"通关月光宝盒IV第{0}波","type":2,"jumpId":1,"jumpId2":34},{"id":419,"name":"通关月光宝盒V第{0}波","type":2,"jumpId":1,"jumpId2":35},{"id":420,"name":"通关月光宝盒VI第{0}波","type":2,"jumpId":1,"jumpId2":36},{"id":421,"name":"通关月光宝盒Ⅶ第{0}波","type":2,"jumpId":1,"jumpId2":37},{"id":422,"name":"通关大圣娶妻I第{0}波","type":2,"jumpId":1,"jumpId2":38},{"id":423,"name":"通关大圣娶妻II第{0}波","type":2,"jumpId":1,"jumpId2":39},{"id":424,"name":"通关大圣娶妻III第{0}波","type":2,"jumpId":1,"jumpId2":40},{"id":425,"name":"通关重启第{0}波","type":2,"jumpId":1,"jumpId2":41},{"id":481,"name":"挑战任意关卡{0}次","type":1,"jumpId":1,"jumpId2":1},{"id":482,"name":"挑战任意秘境{0}次","type":1,"jumpId":1,"jumpId2":43},{"id":501,"name":"任意关卡存活10波{0}次","type":1,"jumpId":1,"jumpId2":44},{"id":502,"name":"任意关卡存活20波{0}次","type":1,"jumpId":1,"jumpId2":45},{"id":503,"name":"任意关卡存活30波{0}次","type":1,"jumpId":1,"jumpId2":46},{"id":504,"name":"任意关卡存活40波{0}次","type":1,"jumpId":1,"jumpId2":47},{"id":505,"name":"任意关卡存活50波{0}次","type":1,"jumpId":1,"jumpId2":48},{"id":506,"name":"任意关卡存活60波{0}次","type":1,"jumpId":1,"jumpId2":49},{"id":507,"name":"任意关卡存活70波{0}次","type":1,"jumpId":1,"jumpId2":50},{"id":508,"name":"任意关卡存活80波{0}次","type":1,"jumpId":1,"jumpId2":51},{"id":611,"name":"升级任意属性{0}次","type":1,"jumpId":2,"jumpId2":52},{"id":621,"name":"提升{0}次境界","type":1,"jumpId":2,"jumpId2":53},{"id":622,"name":"攻击属性升级{0}次","type":1,"jumpId":2,"jumpId2":54},{"id":623,"name":"生命属性升级{0}次","type":1,"jumpId":2,"jumpId2":55},{"id":624,"name":"攻速属性升级{0}次","type":1,"jumpId":2,"jumpId2":56},{"id":625,"name":"吸血属性升级{0}次","type":1,"jumpId":2,"jumpId2":57},{"id":626,"name":"暴击属性升级{0}次","type":1,"jumpId":2,"jumpId2":58},{"id":627,"name":"暴伤属性升级{0}次","type":1,"jumpId":2,"jumpId2":59},{"id":641,"name":"境界达到{0}","type":2,"jumpId":2,"jumpId2":2},{"id":642,"name":"累计升级攻击属性{0}次","type":2,"jumpId":2,"jumpId2":61},{"id":643,"name":"累计升级生命属性{0}次","type":2,"jumpId":2,"jumpId2":62},{"id":644,"name":"累计升级攻速属性{0}次","type":2,"jumpId":2,"jumpId2":63},{"id":645,"name":"累计升级吸血属性{0}次","type":2,"jumpId":2,"jumpId2":64},{"id":646,"name":"累计升级暴击属性{0}次","type":2,"jumpId":2,"jumpId2":65},{"id":647,"name":"累计升级暴伤属性{0}次","type":2,"jumpId":2,"jumpId2":66},{"id":701,"name":"淘秘籍{0}次","type":1,"jumpId":3,"jumpId2":67},{"id":702,"name":"累计淘秘籍{0}次","type":0,"jumpId":3,"jumpId2":68},{"id":703,"name":"解锁{0}个秘籍","type":2,"jumpId":3,"jumpId2":69},{"id":704,"name":"携带{0}次秘籍","type":0,"jumpId":3,"jumpId2":70},{"id":801,"name":"开箱{0}次","type":1,"jumpId":4,"jumpId2":71},{"id":802,"name":"累计开箱{0}次","type":0,"jumpId":4,"jumpId2":72},{"id":803,"name":"强化{0}次任意兵器","type":1,"jumpId":4,"jumpId2":73},{"id":804,"name":"强化{0}次任意兵器","type":0,"jumpId":4,"jumpId2":74},{"id":805,"name":"淬炼{0}次兵器","type":1,"jumpId":4,"jumpId2":75},{"id":806,"name":"淬炼{0}次兵器","type":0,"jumpId":4,"jumpId2":76},{"id":807,"name":"解锁{0}个兵器","type":2,"jumpId":4,"jumpId2":77},{"id":901,"name":"战斗中激活任意阵法{0}次","type":1,"jumpId":1,"jumpId2":78},{"id":902,"name":"升级任意阵法属性{0}次","type":1,"jumpId":5,"jumpId2":79},{"id":911,"name":"乾天阵升到{0}级","type":2,"jumpId":5,"jumpId2":80},{"id":912,"name":"兑泽阵升到{0}级","type":2,"jumpId":5,"jumpId2":81},{"id":913,"name":"离火阵升到{0}级","type":2,"jumpId":5,"jumpId2":82},{"id":914,"name":"震雷阵升到{0}级","type":2,"jumpId":5,"jumpId2":83},{"id":915,"name":"巽风阵升到{0}级","type":2,"jumpId":5,"jumpId2":84},{"id":916,"name":"坎水阵升到{0}级","type":2,"jumpId":5,"jumpId2":85},{"id":917,"name":"艮山阵升到{0}级","type":2,"jumpId":5,"jumpId2":86},{"id":918,"name":"坤地阵升到{0}级","type":2,"jumpId":5,"jumpId2":87},{"id":1001,"name":"进行{0}次金币祝福","type":1,"jumpId":6,"jumpId2":88},{"id":1002,"name":"进行{0}次攻击祝福","type":1,"jumpId":6,"jumpId2":89},{"id":1003,"name":"进行{0}次生命祝福","type":1,"jumpId":6,"jumpId2":90},{"id":1004,"name":"累计进行{0}次祝福","type":0,"jumpId":6,"jumpId2":91},{"id":1201,"name":"挑战{0}次金币副本","type":1,"jumpId":7,"jumpId2":92},{"id":1202,"name":"挑战{0}次钻石副本","type":1,"jumpId":7,"jumpId2":93},{"id":1203,"name":"挑战{0}次阵法副本","type":1,"jumpId":7,"jumpId2":94},{"id":1204,"name":"挑战{0}次强化副本","type":1,"jumpId":7,"jumpId2":95},{"id":1205,"name":"挑战{0}次淬炼副本","type":1,"jumpId":7,"jumpId2":96},{"id":1211,"name":"通关金币副本{0}次","type":0,"jumpId":7,"jumpId2":97},{"id":1212,"name":"通关钻石副本{0}次","type":0,"jumpId":7,"jumpId2":98},{"id":1213,"name":"通关阵法副本{0}次","type":0,"jumpId":7,"jumpId2":99},{"id":1214,"name":"通关强化副本{0}次","type":0,"jumpId":7,"jumpId2":100},{"id":1215,"name":"通关淬炼副本{0}次","type":0,"jumpId":7,"jumpId2":101},{"id":1301,"name":"皮肤升星{0}次","type":0,"jumpId":8,"jumpId2":102},{"id":1302,"name":"解锁{0}个新皮肤","type":2,"jumpId":8,"jumpId2":103},{"id":1303,"name":"升级任意皮肤属性{0}次","type":1,"jumpId":8,"jumpId2":104},{"id":1601,"name":"商城购买{0}次","type":1,"jumpId":9,"jumpId2":105},{"id":1602,"name":"累计商城购买{0}次","type":0,"jumpId":9,"jumpId2":106},{"id":1603,"name":"抽奖{0}次","type":1,"jumpId":10,"jumpId2":107},{"id":1604,"name":"累计抽奖{0}次","type":0,"jumpId":10,"jumpId2":108},{"id":1605,"name":"社区逛逛{0}次","type":1,"jumpId":"","jumpId2":109},{"id":1606,"name":"战斗{0}次","type":0,"jumpId":"","jumpId2":110}]]],0,0,[],[],[]]